imio.fpaudit-0.1.1-py3.11-nspkg.pth
imio/fpaudit/__init__.py
imio/fpaudit/configure.zcml
imio/fpaudit/interfaces.py
imio/fpaudit/logger.py
imio/fpaudit/setuphandlers.py
imio/fpaudit/storage.py
imio/fpaudit/subscribers.py
imio/fpaudit/testing.py
imio/fpaudit/utils.py
imio/fpaudit/browser/__init__.py
imio/fpaudit/browser/configure.zcml
imio/fpaudit/browser/documentgenerator.py
imio/fpaudit/browser/settings.py
imio/fpaudit/profiles/default/browserlayer.xml
imio/fpaudit/profiles/default/controlpanel.xml
imio/fpaudit/profiles/default/metadata.xml
imio/fpaudit/profiles/default/registry.xml
imio/fpaudit/profiles/uninstall/browserlayer.xml
imio/fpaudit/profiles/uninstall/controlpanel.xml
imio/fpaudit/profiles/uninstall/registry.xml
imio/fpaudit/tests/__init__.py
imio/fpaudit/tests/test_browser_settings.py
imio/fpaudit/tests/test_utils.py
imio.fpaudit-0.1.1.dist-info/METADATA
imio.fpaudit-0.1.1.dist-info/WHEEL
imio.fpaudit-0.1.1.dist-info/entry_points.txt
imio.fpaudit-0.1.1.dist-info/namespace_packages.txt
imio.fpaudit-0.1.1.dist-info/top_level.txt
imio.fpaudit-0.1.1.dist-info/RECORD
