Metadata-Version: 2.1
Name: imio.fpaudit
Version: 0.1.1
Summary: This package contains fingerpointing log audit helper.
Home-page: http://pypi.python.org/pypi/imio.fpaudit
Author: IMIO
Author-email: dev@imio.be
License: GPL V2
Keywords: Python Zope Plone
Classifier: Environment :: Web Environment
Classifier: Framework :: Plone
Classifier: Framework :: Plone :: Addon
Classifier: Framework :: Plone :: 4.3
Classifier: Framework :: Plone :: 6.0
Classifier: Programming Language :: Python
Classifier: Programming Language :: Python :: 2.7
Classifier: Programming Language :: Python :: 3.10
Classifier: Operating System :: OS Independent
Classifier: License :: OSI Approved :: GNU General Public License v2 (GPLv2)
Requires-Dist: plone.api
Requires-Dist: setuptools
Requires-Dist: collective.fingerpointing
Requires-Dist: collective.documentgenerator
Provides-Extra: test
Requires-Dist: plone.app.testing ; extra == 'test'
